sparkconnector/__init__.py
sparkconnector/_version.py
sparkconnector/configuration.py
sparkconnector/connector.py
sparkconnector/log4j_conf
sparkconnector/logreader.py
sparkconnector/labextension/package.json
sparkconnector/labextension/static/130.010d2bedc1a53ac02235.js
sparkconnector/labextension/static/211.c41c5accd09bf179f43f.js
sparkconnector/labextension/static/241.a7438870d8deeeebe7f0.js
sparkconnector/labextension/static/241.a7438870d8deeeebe7f0.js.LICENSE.txt
sparkconnector/labextension/static/622.93e439ac1a06053d0c2f.js
sparkconnector/labextension/static/622.93e439ac1a06053d0c2f.js.LICENSE.txt
sparkconnector/labextension/static/64.12c9ec45f5f264202311.js
sparkconnector/labextension/static/747.a7fb8f39c5a4c9909e80.js
sparkconnector/labextension/static/949.deaacecb74692372447f.js
sparkconnector/labextension/static/98.f7f63ca7daba20996bf7.js
sparkconnector/labextension/static/c7afd77757c0cf13826d.png
sparkconnector/labextension/static/remoteEntry.218ec00e7239fc48d371.js
sparkconnector/labextension/static/sparkconnectorui.d70d9d3d69e9a6d6b156.js
sparkconnector/labextension/static/style.js
sparkconnector/labextension/static/third-party-licenses.json
sparkconnector/nbextension/extension.js
sparkconnector/nbextension/extension.js.LICENSE.txt
sparkconnector-3.0.9.data/data/share/jupyter/labextensions/@swan-cern/sparkconnector/package.json
sparkconnector-3.0.9.data/data/share/jupyter/labextensions/@swan-cern/sparkconnector/static/130.010d2bedc1a53ac02235.js
sparkconnector-3.0.9.data/data/share/jupyter/labextensions/@swan-cern/sparkconnector/static/211.c41c5accd09bf179f43f.js
sparkconnector-3.0.9.data/data/share/jupyter/labextensions/@swan-cern/sparkconnector/static/241.a7438870d8deeeebe7f0.js
sparkconnector-3.0.9.data/data/share/jupyter/labextensions/@swan-cern/sparkconnector/static/241.a7438870d8deeeebe7f0.js.LICENSE.txt
sparkconnector-3.0.9.data/data/share/jupyter/labextensions/@swan-cern/sparkconnector/static/622.93e439ac1a06053d0c2f.js
sparkconnector-3.0.9.dist-info/METADATA
sparkconnector-3.0.9.dist-info/WHEEL
sparkconnector-3.0.9.dist-info/top_level.txt
sparkconnector-3.0.9.dist-info/RECORD
